atelier5/__init__.py
atelier5/atelier5.py
atelier5-0.1.dist-info/METADATA
atelier5-0.1.dist-info/WHEEL
atelier5-0.1.dist-info/top_level.txt
atelier5-0.1.dist-info/RECORD
